[{"URL":"http://www.nettiauto.com/mercedes-benz/cla/8079918","ID":null,"make":null,"model":null,"buildYear":null,"plateNumber":null,"drive":null,"transmission":null,"engine":null,"fuelType":null,"milage":null,"firstDate":"2016-06-10T11:12:34.733Z","lastDate":"2016-06-10T11:13:54.000Z","firstPriceInEUR":"37900","lastPriceInEUR":"37900"},{"URL":"http://www.nettiauto.com/mercedes-benz/cla/8087525","ID":null,"make":null,"model":null,"buildYear":null,"plateNumber":null,"drive":null,"transmission":null,"engine":null,"fuelType":null,"milage":null,"firstDate":"2016-06-10T11:12:34.733Z","lastDate":"2016-06-10T11:13:54.000Z","firstPriceInEUR":"37900","lastPriceInEUR":"37900"},{"URL":"http://www.nettiauto.com/mercedes-benz/cla/7746358","ID":null,"make":null,"model":null,"buildYear":null,"plateNumber":null,"drive":null,"transmission":null,"engine":null,"fuelType":null,"milage":null,"firstDate":"2016-06-10T11:12:34.733Z","lastDate":"2016-06-10T11:13:54.000Z","firstPriceInEUR":"38300","lastPriceInEUR":"38300"},{"URL":"http://www.nettiauto.com/mercedes-benz/cla/7836472","ID":null,"make":null,"model":null,"buildYear":null,"plateNumber":null,"drive":null,"transmission":null,"engine":null,"fuelType":null,"milage":null,"firstDate":"2016-06-10T11:12:34.733Z","lastDate":"2016-06-10T11:13:54.000Z","firstPriceInEUR":"38900","lastPriceInEUR":"38900"},{"URL":"http://www.nettiauto.com/mercedes-benz/cla/7865857","ID":null,"make":null,"model":null,"buildYear":null,"plateNumber":null,"drive":null,"transmission":null,"engine":null,"fuelType":null,"milage":null,"firstDate":"2016-06-10T11:12:34.733Z","lastDate":"2016-06-10T11:13:54.000Z","firstPriceInEUR":"38900","lastPriceInEUR":"38900"},{"URL":"http://www.nettiauto.com/mercedes-benz/cla/7770900","ID":null,"make":null,"model":null,"buildYear":null,"plateNumber":null,"drive":null,"transmission":null,"engine":null,"fuelType":null,"milage":null,"firstDate":"2016-06-10T11:12:34.733Z","lastDate":"2016-06-10T11:13:54.000Z","firstPriceInEUR":"39900","lastPriceInEUR":"39900"},{"URL":"http://www.nettiauto.com/mercedes-benz/cla/8063236","ID":null,"make":null,"model":null,"buildYear":null,"plateNumber":null,"drive":null,"transmission":null,"engine":null,"fuelType":null,"milage":null,"firstDate":"2016-06-10T11:12:34.733Z","lastDate":"2016-06-10T11:13:54.000Z","firstPriceInEUR":"39900","lastPriceInEUR":"39900"},{"URL":"http://www.nettiauto.com/mercedes-benz/cla/8074730","ID":null,"make":null,"model":null,"buildYear":null,"plateNumber":null,"drive":null,"transmission":null,"engine":null,"fuelType":null,"milage":null,"firstDate":"2016-06-10T11:12:34.733Z","lastDate":"2016-06-10T11:13:54.000Z","firstPriceInEUR":"39934","lastPriceInEUR":"39934"},{"URL":"http://www.nettiauto.com/mercedes-benz/cla/8081220","ID":null,"make":null,"model":null,"buildYear":null,"plateNumber":null,"drive":null,"transmission":null,"engine":null,"fuelType":null,"milage":null,"firstDate":"2016-06-10T11:12:34.733Z","lastDate":"2016-06-10T11:13:54.000Z","firstPriceInEUR":"39934","lastPriceInEUR":"39934"},{"URL":"http://www.nettiauto.com/mercedes-benz/cla/8081191","ID":null,"make":null,"model":null,"buildYear":null,"plateNumber":null,"drive":null,"transmission":null,"engine":null,"fuelType":null,"milage":null,"firstDate":"2016-06-10T11:12:34.733Z","lastDate":"2016-06-10T11:13:54.000Z","firstPriceInEUR":"40534","lastPriceInEUR":"40534"},{"URL":"http://www.nettiauto.com/mercedes-benz/cla/7826897","ID":null,"make":null,"model":null,"buildYear":null,"plateNumber":null,"drive":null,"transmission":null,"engine":null,"fuelType":null,"milage":null,"firstDate":"2016-06-10T11:12:34.733Z","lastDate":"2016-06-10T11:13:54.000Z","firstPriceInEUR":"40900","lastPriceInEUR":"40900"},{"URL":"http://www.nettiauto.com/mercedes-benz/cla/8070824","ID":null,"make":null,"model":null,"buildYear":null,"plateNumber":null,"drive":null,"transmission":null,"engine":null,"fuelType":null,"milage":null,"firstDate":"2016-06-10T11:12:34.733Z","lastDate":"2016-06-10T11:13:54.000Z","firstPriceInEUR":"40900","lastPriceInEUR":"40900"},{"URL":"http://www.nettiauto.com/mercedes-benz/cla/7652831","ID":null,"make":null,"model":null,"buildYear":null,"plateNumber":null,"drive":null,"transmission":null,"engine":null,"fuelType":null,"milage":null,"firstDate":"2016-06-10T11:12:34.733Z","lastDate":"2016-06-10T11:13:54.000Z","firstPriceInEUR":"41600","lastPriceInEUR":"41600"},{"URL":"http://www.nettiauto.com/mercedes-benz/cla/8027686","ID":null,"make":null,"model":null,"buildYear":null,"plateNumber":null,"drive":null,"transmission":null,"engine":null,"fuelType":null,"milage":null,"firstDate":"2016-06-10T11:12:34.733Z","lastDate":"2016-06-10T11:13:54.000Z","firstPriceInEUR":"41700","lastPriceInEUR":"41700"},{"URL":"http://www.nettiauto.com/mercedes-benz/cla/7585190","ID":null,"make":null,"model":null,"buildYear":null,"plateNumber":null,"drive":null,"transmission":null,"engine":null,"fuelType":null,"milage":null,"firstDate":"2016-06-10T11:12:34.733Z","lastDate":"2016-06-10T11:13:54.000Z","firstPriceInEUR":"41800","lastPriceInEUR":"41800"},{"URL":"http://www.nettiauto.com/mercedes-benz/cla/7755592","ID":null,"make":null,"model":null,"buildYear":null,"plateNumber":null,"drive":null,"transmission":null,"engine":null,"fuelType":null,"milage":null,"firstDate":"2016-06-10T11:12:34.733Z","lastDate":"2016-06-10T11:13:54.000Z","firstPriceInEUR":"41900","lastPriceInEUR":"41900"},{"URL":"http://www.nettiauto.com/mercedes-benz/cla/8030032","ID":null,"make":null,"model":null,"buildYear":null,"plateNumber":null,"drive":null,"transmission":null,"engine":null,"fuelType":null,"milage":null,"firstDate":"2016-06-10T11:12:34.733Z","lastDate":"2016-06-10T11:13:54.000Z","firstPriceInEUR":"41900","lastPriceInEUR":"41900"},{"URL":"http://www.nettiauto.com/mercedes-benz/cla/8016099","ID":null,"make":null,"model":null,"buildYear":null,"plateNumber":null,"drive":null,"transmission":null,"engine":null,"fuelType":null,"milage":null,"firstDate":"2016-06-10T11:12:34.733Z","lastDate":"2016-06-10T11:13:54.000Z","firstPriceInEUR":"42700","lastPriceInEUR":"42700"},{"URL":"http://www.nettiauto.com/mercedes-benz/cla/7855509","ID":null,"make":null,"model":null,"buildYear":null,"plateNumber":null,"drive":null,"transmission":null,"engine":null,"fuelType":null,"milage":null,"firstDate":"2016-06-10T11:12:34.733Z","lastDate":"2016-06-10T11:13:54.000Z","firstPriceInEUR":"42800","lastPriceInEUR":"42800"},{"URL":"http://www.nettiauto.com/mercedes-benz/cla/7744255","ID":null,"make":null,"model":null,"buildYear":null,"plateNumber":null,"drive":null,"transmission":null,"engine":null,"fuelType":null,"milage":null,"firstDate":"2016-06-10T11:12:34.733Z","lastDate":"2016-06-10T11:13:54.000Z","firstPriceInEUR":"42900","lastPriceInEUR":"42900"},{"URL":"http://www.nettiauto.com/mercedes-benz/cla/8049231","ID":null,"make":null,"model":null,"buildYear":null,"plateNumber":null,"drive":null,"transmission":null,"engine":null,"fuelType":null,"milage":null,"firstDate":"2016-06-10T11:12:34.733Z","lastDate":"2016-06-10T11:13:54.000Z","firstPriceInEUR":"42900","lastPriceInEUR":"42900"},{"URL":"http://www.nettiauto.com/mercedes-benz/cla/7771576","ID":null,"make":null,"model":null,"buildYear":null,"plateNumber":null,"drive":null,"transmission":null,"engine":null,"fuelType":null,"milage":null,"firstDate":"2016-06-10T11:12:34.733Z","lastDate":"2016-06-10T11:13:54.000Z","firstPriceInEUR":"44900","lastPriceInEUR":"44900"},{"URL":"http://www.nettiauto.com/mercedes-benz/cla/8082438","ID":null,"make":null,"model":null,"buildYear":null,"plateNumber":null,"drive":null,"transmission":null,"engine":null,"fuelType":null,"milage":null,"firstDate":"2016-06-10T11:12:34.733Z","lastDate":"2016-06-10T11:13:54.000Z","firstPriceInEUR":"45800","lastPriceInEUR":"45800"},{"URL":"http://www.nettiauto.com/mercedes-benz/cla/7677385","ID":null,"make":null,"model":null,"buildYear":null,"plateNumber":null,"drive":null,"transmission":null,"engine":null,"fuelType":null,"milage":null,"firstDate":"2016-06-10T11:12:34.733Z","lastDate":"2016-06-10T11:13:54.000Z","firstPriceInEUR":"45900","lastPriceInEUR":"45900"},{"URL":"http://www.nettiauto.com/mercedes-benz/cla/7870876","ID":null,"make":null,"model":null,"buildYear":null,"plateNumber":null,"drive":null,"transmission":null,"engine":null,"fuelType":null,"milage":null,"firstDate":"2016-06-10T11:12:34.733Z","lastDate":"2016-06-10T11:13:54.000Z","firstPriceInEUR":"45900","lastPriceInEUR":"45900"},{"URL":"http://www.nettiauto.com/mercedes-benz/cla/7992493","ID":null,"make":null,"model":null,"buildYear":null,"plateNumber":null,"drive":null,"transmission":null,"engine":null,"fuelType":null,"milage":null,"firstDate":"2016-06-10T11:12:34.733Z","lastDate":"2016-06-10T11:13:54.000Z","firstPriceInEUR":"46202","lastPriceInEUR":"46202"},{"URL":"http://www.nettiauto.com/mercedes-benz/cla/7835174","ID":null,"make":null,"model":null,"buildYear":null,"plateNumber":null,"drive":null,"transmission":null,"engine":null,"fuelType":null,"milage":null,"firstDate":"2016-06-10T11:12:34.733Z","lastDate":"2016-06-10T11:13:54.000Z","firstPriceInEUR":"51793","lastPriceInEUR":"51793"},{"URL":"http://www.nettiauto.com/mercedes-benz/cla/7906278","ID":null,"make":null,"model":null,"buildYear":null,"plateNumber":null,"drive":null,"transmission":null,"engine":null,"fuelType":null,"milage":null,"firstDate":"2016-06-10T11:12:34.733Z","lastDate":"2016-06-10T11:13:54.000Z","firstPriceInEUR":"51900","lastPriceInEUR":"51900"},{"URL":"http://www.nettiauto.com/mercedes-benz/cla/7695294","ID":null,"make":null,"model":null,"buildYear":null,"plateNumber":null,"drive":null,"transmission":null,"engine":null,"fuelType":null,"milage":null,"firstDate":"2016-06-10T11:12:34.733Z","lastDate":"2016-06-10T11:13:54.000Z","firstPriceInEUR":"53900","lastPriceInEUR":"53900"},{"URL":"http://www.nettiauto.com/mercedes-benz/cla/8082401","ID":null,"make":null,"model":null,"buildYear":null,"plateNumber":null,"drive":null,"transmission":null,"engine":null,"fuelType":null,"milage":null,"firstDate":"2016-06-10T11:12:34.733Z","lastDate":"2016-06-10T11:13:54.000Z","firstPriceInEUR":"79900","lastPriceInEUR":"79900"}]
